klein/__init__.py
klein/_app.py
klein/_attrs_zope.py
klein/_decorators.py
klein/_dihttp.py
klein/_form.py
klein/_headers.py
klein/_headers_compat.py
klein/_iform.py
klein/_imessage.py
klein/_interfaces.py
klein/_isession.py
klein/_message.py
klein/_plating.py
klein/_request.py
klein/_request_compat.py
klein/_requirer.py
klein/_resource.py
klein/_response.py
klein/_session.py
klein/_tubes.py
klein/_typing_compat.py
klein/_version.py
klein/app.py
klein/interfaces.py
klein/py.typed
klein/resource.py
klein/storage/__init__.py
klein/storage/_memory.py
klein/storage/memory.py
klein/test/__init__.py
klein/test/_trial.py
klein/test/not_hypothesis.py
klein/test/test_app.py
klein/test/test_attrs_zope.py
klein/test/test_exports.py
klein/test/test_form.py
klein/test/test_headers.py
klein/test/test_headers_compat.py
klein/test/test_memory.py
klein/test/test_message.py
klein/test/test_plating.py
klein/test/test_request.py
klein/test/test_request_compat.py
klein/test/test_requirer.py
klein/test/test_resource.py
klein/test/test_response.py
klein/test/test_session.py
klein/test/test_trial.py
klein/test/typing_app.py
klein/test/util.py
klein-24.8.0.dist-info/AUTHORS
klein-24.8.0.dist-info/LICENSE
klein-24.8.0.dist-info/METADATA
klein-24.8.0.dist-info/WHEEL
klein-24.8.0.dist-info/top_level.txt
klein-24.8.0.dist-info/RECORD
