Metadata-Version: 2.1
Name: klein
Version: 24.8.0
Summary: werkzeug + twisted.web
Home-page: https://github.com/twisted/klein
Maintainer: Twisted Matrix Laboratories
Maintainer-email: twisted@python.org
License: MIT
Keywords: twisted flask werkzeug web
Classifier: Environment :: Web Environment
Classifier: Intended Audience :: Developers
Classifier: License :: OSI Approved :: MIT License
Classifier: Operating System :: OS Independent
Classifier: Programming Language :: Python
Classifier: Programming Language :: Python :: 3.7
Classifier: Programming Language :: Python :: 3.8
Classifier: Programming Language :: Python :: 3.9
Classifier: Programming Language :: Python :: 3.10
Classifier: Programming Language :: Python :: 3.11
Classifier: Programming Language :: Python :: Implementation :: CPython
Classifier: Programming Language :: Python :: Implementation :: PyPy
Classifier: Topic :: Internet :: WWW/HTTP :: Dynamic Content
Classifier: Topic :: Software Development :: Libraries :: Python Modules
Requires-Python: >=3.7
License-File: LICENSE
License-File: AUTHORS
Requires-Dist: attrs>=20.1.0
Requires-Dist: hyperlink
Requires-Dist: incremental
Requires-Dist: Tubes
Requires-Dist: Twisted>=16.6
Requires-Dist: typing_extensions; python_version < "3.10"
Requires-Dist: Werkzeug
Requires-Dist: zope.interface
